src/__init__.py
src/cli.py
src/config.py
src/main_runner.py
src/agent/__init__.py
src/agent/codiac_agent.py
src/api/__init__.py
src/api/handlers.py
src/api/handlers_BACKUP.py
src/api/handlers_BROKEN.py
src/api/handlers_FINAL_FIX.py
src/api/handlers_ULTIMATE_FIX.py
src/api/handlers_WITH_DEBUG.py
src/core/__init__.py
src/core/caching.py
src/core/claude_md_reader.py
src/core/command_handler.py
src/core/context_cache.py
src/core/devstral_tools.py
src/core/devstral_tools_secure.py
src/core/ollama_client.py
src/core/os_detection.py
src/core/permission_manager.py
src/core/session_manager.py
src/web/index.html
src/web/static/css/performance.css
src/web/static/css/security.css
src/web/static/css/style.css
src/web/static/js/app.js
src/web/static/js/security.js
ollama_code-0.5.2.dist-info/METADATA
ollama_code-0.5.2.dist-info/WHEEL
ollama_code-0.5.2.dist-info/entry_points.txt
ollama_code-0.5.2.dist-info/top_level.txt
ollama_code-0.5.2.dist-info/RECORD
