Metadata-Version: 2.4
Name: ollama-code
Version: 0.5.2
Summary: Ein autonomer KI-Entwicklungsassistent mit lokalem Ollama-Backend.
Author-email: Dein Name <deine@email.com>
License-Expression: MIT
Project-URL: Homepage, https://github.com/dein-username/openai-coder
Project-URL: Bug Tracker, https://github.com/dein-username/openai-coder/issues
Classifier: Programming Language :: Python :: 3
Classifier: Operating System :: OS Independent
Classifier: Development Status :: 4 - Beta
Classifier: Environment :: Web Environment
Classifier: Intended Audience :: Developers
Classifier: Topic :: Scientific/Engineering :: Artificial Intelligence
Classifier: Topic :: Software Development
Requires-Python: >=3.9
Requires-Dist: eel>=0.14.0
Requires-Dist: requests>=2.28.0
